axonify/__init__.py
axonify/axonify.py
axonify/func.py
axonify-7.6.dist-info/METADATA
axonify-7.6.dist-info/WHEEL
axonify-7.6.dist-info/top_level.txt
axonify-7.6.dist-info/RECORD
