Metadata-Version: 2.2
Name: axonify
Version: 7.6
Summary: Axonify is a versatile Python library designed to provide a comprehensive suite of utilities for system operations, file management, and logging. It is particularly useful for developers who need to perform complex tasks with minimal setup and overhead. Axonify includes advanced logging capabilities, file operations, system information retrieval, and more, making it a powerful tool for a wide range of applications.
Classifier: Programming Language :: Python :: 3
Classifier: License :: OSI Approved :: MIT License
Classifier: Operating System :: OS Independent
Requires-Python: >=3
Requires-Dist: requests
Requires-Dist: pybase64
Requires-Dist: importlib
Dynamic: classifier
Dynamic: description
Dynamic: description-content-type
Dynamic: requires-dist
Dynamic: requires-python
Dynamic: summary
